klavis/__init__.py
klavis/amplitude_oauth/__init__.py
klavis/amplitude_oauth/client.py
klavis/amplitude_oauth/raw_client.py
klavis/client.py
klavis/clockwise_oauth/__init__.py
klavis/clockwise_oauth/client.py
klavis/clockwise_oauth/raw_client.py
klavis/core/__init__.py
klavis/core/api_error.py
klavis/core/client_wrapper.py
klavis/core/datetime_utils.py
klavis/core/file.py
klavis/core/force_multipart.py
klavis/core/http_client.py
klavis/core/http_response.py
klavis/core/http_sse/__init__.py
klavis/core/http_sse/_api.py
klavis/core/http_sse/_decoders.py
klavis/core/http_sse/_exceptions.py
klavis/core/http_sse/_models.py
klavis/core/jsonable_encoder.py
klavis/core/pydantic_utilities.py
klavis/core/query_encoder.py
klavis/core/remove_none_from_dict.py
klavis/core/request_options.py
klavis/core/serialization.py
klavis/environment.py
klavis/errors/__init__.py
klavis/errors/bad_request_error.py
klavis/errors/unprocessable_entity_error.py
klavis/google_cloud_oauth/__init__.py
klavis/google_cloud_oauth/client.py
klavis/google_cloud_oauth/raw_client.py
klavis/google_forms_oauth/__init__.py
klavis/google_forms_oauth/client.py
klavis/google_forms_oauth/raw_client.py
klavis/honeycomb_oauth/__init__.py
klavis/honeycomb_oauth/client.py
klavis/honeycomb_oauth/raw_client.py
klavis/huggingface_oauth/__init__.py
klavis/huggingface_oauth/client.py
klavis/huggingface_oauth/raw_client.py
klavis/instagram_oauth/__init__.py
klavis/instagram_oauth/client.py
klavis/instagram_oauth/raw_client.py
klavis/intercom_oauth/__init__.py
klavis/intercom_oauth/client.py
klavis/intercom_oauth/raw_client.py
klavis/jotform_oauth/__init__.py
klavis/jotform_oauth/client.py
klavis/jotform_oauth/raw_client.py
klavis/mcp_server/__init__.py
klavis/mcp_server/client.py
klavis/mcp_server/raw_client.py
klavis/mcp_server/types/__init__.py
klavis/mcp_server/types/authdata.py
klavis/mcp_server/types/delete_servers_from_strata_mcp_server_strata_strata_id_servers_delete_request_servers_item.py
klavis-2.20.0.dist-info/LICENSE
klavis-2.20.0.dist-info/METADATA
klavis-2.20.0.dist-info/WHEEL
klavis-2.20.0.dist-info/RECORD
